altruistclient/__init__.py
altruistclient/client.py
altruistclient/discoverer.py
altruistclient/errors.py
altruistclient/model.py
altruistclient-0.1.0.dist-info/LICENSE
altruistclient-0.1.0.dist-info/METADATA
altruistclient-0.1.0.dist-info/WHEEL
altruistclient-0.1.0.dist-info/RECORD
