Metadata-Version: 2.3
Name: altruistclient
Version: 0.1.0
Summary: Async library for discovering and fetching data from Altruist sensors
License: Apache-2.0
Author: Alena Bugrova
Author-email: bugrovaad@gmail.com
Requires-Python: >=3.9,<4.0
Classifier: License :: OSI Approved :: Apache Software License
Classifier: Programming Language :: Python :: 3
Classifier: Programming Language :: Python :: 3.9
Classifier: Programming Language :: Python :: 3.10
Classifier: Programming Language :: Python :: 3.11
Classifier: Programming Language :: Python :: 3.12
Classifier: Programming Language :: Python :: 3.13
Requires-Dist: aiohttp (>=3.11.0,<4.0.0)
Requires-Dist: zeroconf (>=0.143.0,<1.0.0)
Project-URL: Repository, https://github.com/LoSk-p/altruistclient
